Workbook
Name adj_HR: trt_engine!#REF!
Name adj_OS_Prob: trt_engine!$N$4:$N$363
Name adj_OS_Prob: soc_engine!$N$4:$N$363
Name Age: soc_engine!$B$4:$B$363
Name asdfasdf: inputs!$M$11
Name base_HR: inputs!#REF!
Name crrct_dth_risk: trt_engine!$M$4:$M$363
Name crrct_dth_risk: soc_engine!$M$4:$M$363
Name Cycle: soc_engine!$A$4:$A$363
Name cycle_length: inputs!$B$2
Name delta_C: Dashboard_Summary!$B$3
Name delta_E: Dashboard_Summary!$B$2
Name disc_rate_clum: trt_engine!$C$2:$C$363
Name disc_rate_clum: soc_engine!$C$4:$C$363
Name Disc_rate_per_cyc: inputs!$B$5
Name Discount_rate: inputs!$B$4
Name hcc_qal_per_cyc: trt_engine!$W$4:$W$363
Name hcc_qal_per_cyc: soc_engine!$W$4:$W$363
Name hr_os_mu: inputs!$G$12
Name hr_os_sigma: inputs!$H$12
Name hr_os_VtUs: inputs!$M$12
Name hr_pfs_mu: inputs!$G$11
Name hr_pfs_sigma: inputs!$H$11
Name hr_pfs_VtUs: inputs!$M$11
Name ICER: Dashboard_Summary!$B$4
Name Impl_dth_rsk: trt_engine!$K$4:$K$363
Name Impl_dth_rsk: soc_engine!$K$4:$K$363
Name Mntr_Adm_cst: inputs!$B$15
Name Mntr_Adm_cst_mu: inputs!$G$10
Name Mntr_Adm_cst_sigma: inputs!$H$10
Name Mntr_Adm_cst_VtUs: inputs!$M$10
Name ons_dth_risk: trt_engine!$L$4:$L$363
Name ons_dth_risk: soc_engine!$L$4:$L$363
Name pd_chm_price: inputs!$B$12
Name pd_chm_share: inputs!$D$19
Name pd_mAb_price: inputs!$B$11
Name pd_mAb_share: inputs!$D$18
Name pd_ulty_mu: inputs!$G$8
Name pd_ulty_sigma: inputs!$H$8
Name pd_ulty_VtUs: inputs!$M$8
Name pfs_ulty_mu: inputs!$G$7
Name pfs_ulty_sigma: inputs!$H$7
Name pfs_ulty_VtUs: inputs!$M$7
Name psa_hrscl_pfs_VtUs: inputs!$M$11
Name PSA_Soc_OSHR_scaler: inputs!$G$14
Name PSA_Soc_PFSHR_scaler: inputs!$G$12
Name psa_soc_pfshr_sclr: inputs!$M$12
Name PSA_SocHRsclr_os_VtUs: inputs!$M$14
Name PSA_SocHRsclr_pfs_VtUs: inputs!$M$12
Name PSA_Switch: inputs!$J$1
Name PSA_trt_OSHR_scaler: inputs!$G$13
Name PSA_trt_PFSHR_scaler: inputs!$G$11
Name psa_trt_pfshr_sclr: inputs!$M$11
Name PSA_trtHRsclr_os_VtUs: inputs!$M$13
Name PSA_trtHRsclr_pfs_VtUs: inputs!$M$11
Name soc_COST: soc_engine!$Z$4
Name soc_dth: soc_engine!$Q$4:$Q$363
Name soc_OS_Prob: soc_engine!$H$4:$H$363
Name soc_OS_State: #REF!
Name soc_OS_weibull_scale: inputs!#REF!

Sheet Dashboard_Summary
A2: ∆E | B2: =trt_QALY-soc_QALY -> 0.64957294
A3: ∆C | B3: =trt_COST-soc_COST -> 34761.182
A4: ICER | B4: =B3/B2 -> 53513.901
A6: ∆E Prob | B6: =AVERAGE(PSA_Dashboard!C11:C1010) -> 0.64655779
A7: ∆C Prob | B7: =AVERAGE(PSA_Dashboard!B11:B1010) -> 34918.248
A8: ICER Prob | B8: =B7/B6 -> 54006.384
A10: Logical Health Check
A11: Soc OS/PFS Check | B11: {=IF(MIN(soc_OS_Prob-soc_PFS_Prob) < 0, "🚩 Biological Error", "✅ Valid")} -> ✅ Valid
A12: Trt OS/PFS Check | B12: {=IF(MIN(trt_OS_Prob-trt_PFS_Prob) < 0, "🚩 Biological Error", "✅ Valid")} -> ✅ Valid
A13: Soc Cohort Balance Check | B13: =IF(AND(MIN(soc_engine!R2:R362) > 0.9999, MAX(soc_engine!R2:R362) < 1.0001), "✅ Balanced", "🚩 Balance Error") -> ✅ Balanced
A14: Trt Cohort Balance Check | B14: =IF(AND(MIN(trt_engine!R2:R362) > 0.9999, MAX(trt_engine!R2:R362) < 1.0001), "✅ Balanced", "🚩 Balance Error") -> ✅ Balanced
A15: WTP_Threshold (£30,000) | B15: =IF(B4 <= 30000, "✅ Cost-Effective", "❌ Not Cost-Effective") -> ❌ Not Cost-Effective
A17: Drug A Net Price | B17: =trt_lst_price*(1-trt_pas_disc) -> 1050
A18: Implied HR @ 60m | B18: 0.4916
A19: Waning Duration | B19: 60

Sheet PSA_Dashboard
B1: ΔC | C1: ΔE | D1: NMB @ WTP30k | E1: Mean | G1: WTP Threshold | H1: Probability CE
B2: 32110.456 | C2: 0.62465222 | D2: -13370.89 | E2: =AVERAGE($D:$D) -> -15516.684 | G2: 0 | H2: {=SUMPRODUCT(--(($C$2:$C$1001 * G2 - $B$2:$B$1001) > 0)) / 1000} -> 0
A3: 1 | B3: 26010.406 | C3: 0.7601442 | D3: -3206.0799 | G3: 5000 | H3: {=SUMPRODUCT(--(($C$2:$C$1001 * G3 - $B$2:$B$1001) > 0)) / 1000} -> 0
A4: 2 | B4: 43703.061 | C4: 0.51844324 | D4: -28149.764 | G4: 10000 | H4: {=SUMPRODUCT(--(($C$2:$C$1001 * G4 - $B$2:$B$1001) > 0)) / 1000} -> 0
A5: 3 | B5: 30306.469 | C5: 0.62061569 | D5: -11687.999 | G5: 15000 | H5: {=SUMPRODUCT(--(($C$2:$C$1001 * G5 - $B$2:$B$1001) > 0)) / 1000} -> 0
A6: 4 | B6: 46723.681 | C6: 0.80118704 | D6: -22688.07 | G6: 20000 | H6: {=SUMPRODUCT(--(($C$2:$C$1001 * G6 - $B$2:$B$1001) > 0)) / 1000} -> 0.003
A7: 5 | B7: 25828.547 | C7: 0.52071107 | D7: -10207.215 | G7: 25000 | H7: {=SUMPRODUCT(--(($C$2:$C$1001 * G7 - $B$2:$B$1001) > 0)) / 1000} -> 0.016
A8: 6 | B8: 37826.523 | C8: 0.4707353 | D8: -23704.464 | G8: 30000 | H8: {=SUMPRODUCT(--(($C$2:$C$1001 * G8 - $B$2:$B$1001) > 0)) / 1000} -> 0.05
A9: 7 | B9: 27013.086 | C9: 0.44702486 | D9: -13602.34 | G9: 35000 | H9: {=SUMPRODUCT(--(($C$2:$C$1001 * G9 - $B$2:$B$1001) > 0)) / 1000} -> 0.113
A10: 8 | B10: 31543.571 | C10: 0.77672689 | D10: -8241.7645 | G10: 40000 | H10: {=SUMPRODUCT(--(($C$2:$C$1001 * G10 - $B$2:$B$1001) > 0)) / 1000} -> 0.182 | Q10: X (QALYs) | R10: Y (Costs)
A11: 9 | B11: 45916.71 | C11: 0.89730803 | D11: -18997.469 | G11: 45000 | H11: {=SUMPRODUCT(--(($C$2:$C$1001 * G11 - $B$2:$B$1001) > 0)) / 1000} -> 0.292 | Q11: 0 | R11: 0
A12: 10 | B12: 29247.903 | C12: 0.90367433 | D12: -2137.673 | G12: 50000 | H12: {=SUMPRODUCT(--(($C$2:$C$1001 * G12 - $B$2:$B$1001) > 0)) / 1000} -> 0.406 | Q12: 1.6 | R12: 48000
A13: 11 | B13: 20698.448 | C13: 0.45228898 | D13: -7129.7786 | G13: 55000 | H13: {=SUMPRODUCT(--(($C$2:$C$1001 * G13 - $B$2:$B$1001) > 0)) / 1000} -> 0.523
A14: 12 | B14: 29667.093 | C14: 0.67115563 | D14: -9532.4247 | G14: 60000 | H14: {=SUMPRODUCT(--(($C$2:$C$1001 * G14 - $B$2:$B$1001) > 0)) / 1000} -> 0.633
A15: 13 | B15: 33179.344 | C15: 0.98684001 | D15: -3574.1439 | G15: 65000 | H15: {=SUMPRODUCT(--(($C$2:$C$1001 * G15 - $B$2:$B$1001) > 0)) / 1000} -> 0.699
A16: 14 | B16: 47888.218 | C16: 1.1800842 | D16: -12485.692 | G16: 70000 | H16: {=SUMPRODUCT(--(($C$2:$C$1001 * G16 - $B$2:$B$1001) > 0)) / 1000} -> 0.764
A17: 15 | B17: 36183.479 | C17: 0.77155361 | D17: -13036.871 | G17: 75000 | H17: {=SUMPRODUCT(--(($C$2:$C$1001 * G17 - $B$2:$B$1001) > 0)) / 1000} -> 0.819
A18: 16 | B18: 34387.946 | C18: 0.57827801 | D18: -17039.606 | G18: 80000 | H18: {=SUMPRODUCT(--(($C$2:$C$1001 * G18 - $B$2:$B$1001) > 0)) / 1000} -> 0.859
A19: 17 | B19: 40638.348 | C19: 0.73767677 | D19: -18508.044 | G19: 85000 | H19: {=SUMPRODUCT(--(($C$2:$C$1001 * G19 - $B$2:$B$1001) > 0)) / 1000} -> 0.882
A20: 18 | B20: 23897.69 | C20: 0.3585962 | D20: -13139.804 | G20: 90000 | H20: {=SUMPRODUCT(--(($C$2:$C$1001 * G20 - $B$2:$B$1001) > 0)) / 1000} -> 0.899
A21: 19 | B21: 28157.726 | C21: 0.71740129 | D21: -6635.6873 | G21: 95000 | H21: {=SUMPRODUCT(--(($C$2:$C$1001 * G21 - $B$2:$B$1001) > 0)) / 1000} -> 0.928
A22: 20 | B22: 21655.459 | C22: 0.42012465 | D22: -9051.7193 | G22: 100000 | H22: {=SUMPRODUCT(--(($C$2:$C$1001 * G22 - $B$2:$B$1001) > 0)) / 1000} -> 0.942
A23: 21 | B23: 41372.199 | C23: 1.0047672 | D23: -11229.183
A24: 22 | B24: 32071.181 | C24: 0.54957632 | D24: -15583.892
A25: 23 | B25: 26411.869 | C25: 0.51533409 | D25: -10951.846
A26: 24 | B26: 28237.208 | C26: 0.69537587 | D26: -7375.9321
A27: 25 | B27: 26378.326 | C27: 0.60541753 | D27: -8215.8003
A28: 26 | B28: 22310.738 | C28: 0.57544451 | D28: -5047.4029
A29: 27 | B29: 25906.183 | C29: 0.82663022 | D29: -1107.2763
A30: 28 | B30: 39293.936 | C30: 0.34772412 | D30: -28862.212
A31: 29 | B31: 20242.273 | C31: 0.54723465 | D31: -3825.2337
A32: 30 | B32: 37516.389 | C32: 0.70574444 | D32: -16344.056
A33: 31 | B33: 33184.831 | C33: 0.49260456 | D33: -18406.695
A34: 32 | B34: 30041.919 | C34: 0.8641186 | D34: -4118.3608
... A1002: 1000 | B1002: 28877.961 | C1002: 0.75259058 | D1002: -6300.2438

Sheet inputs
A1: time_horizion | B1: 30 | C1: Years | F1: Probabilistic Sensitivity Analysis | I1: PSA_Switch | J1: 0
A2: cycle_length | B2: 1 | C2: Month
A3: start_age | B3: 65
A4: Discount_rate | B4: 0.035 | C4: Annual
A5: Disc_rate_per_cyc | B5: =(1+$B$4)^(1/12)-1 -> 0.0028708987 | C5: Per Month
A6: trt_lst_price | B6: 3500 | C6: Per Month | G6: mu | H6: sigma | I6: Distribution | J6: Parameter 1 | K6: Parameter 2 | L6: Random Draw | M6: Value to Use
A7: trt_pas_disc | B7: 0.7 | F7: pfs_ulty | G7: 0.78 | H7: 0.05 | I7: Beta | J7: =pfs_ulty_mu*(pfs_ulty_mu*((1-pfs_ulty_mu)/pfs_ulty_sigma^2)-1) -> 52.7592 | K7: =(1-pfs_ulty_mu)*(pfs_ulty_mu*((1-pfs_ulty_mu)/pfs_ulty_sigma^2)-1) -> 14.8808 | L7: =_xlfn.BETA.INV(RAND(),J7,K7) -> 0.8498739 | M7: =IF(PSA_Switch=0,pfs_ulty_mu,L7) -> 0.78
A8: trt_cap_month | B8: 24 | C8: Month | F8: pd_ulty | G8: 0.5 | H8: 0.05 | I8: Beta | J8: =pd_ulty_mu*(pd_ulty_mu*((1-pd_ulty_mu)/pd_ulty_sigma^2)-1) -> 49.5 | K8: =(1-pd_ulty_mu)*(pd_ulty_mu*((1-pd_ulty_mu)/pd_ulty_sigma^2)-1) -> 49.5 | L8: =_xlfn.BETA.INV(RAND(),J8,K8) -> 0.42924733 | M8: =IF(PSA_Switch=0,pd_ulty_mu,L8) -> 0.5
A9: soc_price | B9: 2200 | C9: Per Month | F9: Subsq_PD_cst | G9: =pd_mAb_price*B13+pd_chm_price*B14 -> 850 | H9: 240 | I9: Gamma | J9: =Subsq_PD_cst_mu^2/Subsq_PD_cst_sigma^2 -> 12.543403 | K9: =Subsq_PD_cst_sigma^2/Subsq_PD_cst_mu -> 67.764706 | L9: =_xlfn.GAMMA.INV(RAND(),J9,K9) -> 1416.9732 | M9: =IF(PSA_Switch=0,Subsq_PD_cst_mu,L9) -> 850
F10: Mntr_Adm_cst | G10: =Mntr_Adm_cst -> 200 | H10: 40 | I10: Gamma | J10: =Mntr_Adm_cst_mu^2/Mntr_Adm_cst_sigma^2 -> 25 | K10: =Mntr_Adm_cst_sigma^2/Mntr_Adm_cst_mu -> 8 | L10: =_xlfn.GAMMA.INV(RAND(),J10,K10) -> 133.17276 | M10: =IF(PSA_Switch=0,Mntr_Adm_cst_mu,L10) -> 200
A11: pd_mAb_price | B11: 4000 | C11: /Month | F11: PSA_trt_PFSHR_scaler | G11: 1 | I11: Log Normal | L11: =_xlfn.LOGNORM.INV(RAND(), LN(1), 0.1) -> 1.0502377 | M11: =IF(PSA_Switch=0,1,L11) -> 1
A12: pd_chm_price | B12: 500 | C12: /Month | F12: PSA_Soc_PFSHR_scaler | G12: 1 | I12: Log Normal | L12: =_xlfn.LOGNORM.INV(RAND(), LN(1), 0.1) -> 0.95047459 | M12: =IF(PSA_Switch=0,1,L12) -> 1
A13: pd_mAb_share | B13: 0.1 | C13: Share in a Month | F13: PSA_trt_OSHR_scaler | G13: 1 | I13: Log Normal | L13: =_xlfn.LOGNORM.INV(RAND(), LN(1), 0.1) -> 0.96341815 | M13: =IF(PSA_Switch=0,1,L13) -> 1
A14: pd_chm_share | B14: 0.9 | C14: Share in a Month | F14: PSA_Soc_OSHR_scaler | G14: 1 | I14: Log Normal | L14: =_xlfn.LOGNORM.INV(RAND(), LN(1), 0.1) -> 1.049348 | M14: =IF(PSA_Switch=0,1,L14) -> 1
A15: Mntr_Adm_cst | B15: 200 | F15: STAN_HR_RND_INX
A16: Utlty_PFS | B16: 0.78
A17: Utlty_PD | B17: 0.6
A18: Utlty_AE_Disutlt | B18: -0.1

Sheet RRMM_Model_Inputs
A1: Month | B1: SoC_PFS | C1: SoC_OS | D1: Trt_PFS | E1: Trt_OS
A2: 0 | B2: 1 | C2: 1 | D2: 1 | E2: 1
A3: 1 | B3: 0.96078944 | C3: 0.98216103 | D3: 0.97530991 | E3: 0.99004983
A4: 2 | B4: 0.91220013 | C4: 0.96215103 | D4: 0.94782189 | E4: 0.97950758
A5: 3 | B5: 0.86114902 | C5: 0.94150968 | D5: 0.91969863 | E5: 0.96880297
A6: 4 | B6: 0.80967587 | C6: 0.92062151 | D6: 0.89148218 | E6: 0.95803503
A7: 5 | B7: 0.75885396 | C7: 0.89968039 | D7: 0.86344302 | E7: 0.94725219
A8: 6 | B8: 0.7093313 | C8: 0.87880437 | D8: 0.83574254 | E8: 0.93648347
A9: 7 | B9: 0.66151906 | C9: 0.8580726 | D9: 0.80848556 | E9: 0.92574818
A10: 8 | B10: 0.61567916 | C10: 0.83754122 | D10: 0.78174328 | E10: 0.91506008
A11: 9 | B11: 0.57197248 | C11: 0.81725149 | D11: 0.755565 | E11: 0.90442935
A12: 10 | B12: 0.53048835 | C12: 0.79723437 | D12: 0.72998496 | E12: 0.89386382
A13: 11 | B13: 0.49126407 | C13: 0.77751343 | D13: 0.70502646 | E13: 0.88336959
... A362: 360 | B362: 5.0599618e-21 | C362: 8.5155893e-06 | D362: 9.9821936e-19 | E362: 3.4645547e-05

Sheet soc_engine
A1: Cycle | B1: Patient Age (Years) | C1: Cumulative Discount Factor | D1: SoC PFS Probability | E1: SoC Progression Risk | F1: SoC PSA PFS Hazard | G1: SoC PFS Probability PSA adj | H1: SoC OS Probability | I1: SoC PSA OS Hazard | J1: SoC OS Probability PSA adj | K1: Implied Death Risk | L1: ONS Mortality Risk | M1: Corrected Death Risk | N1: Adjusted OS Probability | O1: SoC PFS Membership | P1: SoC Progressed Membership | Q1: SoC Death Membership | R1: Sum Check | S1: SoC PFS Cost (£) | T1: SoC Subsequent Cost (£) | U1: SoC Total Cost (HCC) (£) | V1: SoC Utility | W1: SoC QALYs (HCC)
A2: Cycle | B2: Age | C2: disc_rate_clum | D2: soc_PFS_Prob | E2: soc_prog_risk | F2: soc_PSA_PFS_hazard | G2: soc_PFS_Prob_psa_adj | H2: soc_OS_Prob | I2: soc_PSA_OS_hazard | J2: soc_OS_Prob_psa_adj | K2: Impl_dth_rsk | L2: ons_dth_risk | M2: crrct_dth_risk | N2: adj_OS_Prob | O2: soc_pfs_stt | P2: soc_pd_stt | Q2: soc_dth | R2: sum_check | S2: soc_pfs_cst | T2: soc_pd_cst | U2: hccsoc_ttl_cst | V2: soc_utl | W2: hcc_qal_per_cyc
A3: 0 | B3: =(start_age*12+A3)/12 -> 65 | C3: =1/(1+Disc_rate_per_cyc)^$A3 -> 1 | D3: {=_xlfn.XLOOKUP(A3:A363,'RRMM_Model_Inputs'!A2:A362,'RRMM_Model_Inputs'!B2:B362)} -> 1 | G3: 1 | H3: {=_xlfn.XLOOKUP(A3:A363,'RRMM_Model_Inputs'!A2:A362,'RRMM_Model_Inputs'!C2:C362)} -> 1 | J3: 1 | N3: 1 | O3: {=soc_PFS_Prob_psa_adj} -> 1 | Q3: =1-N3 -> 0 | R3: =SUM(O3:Q3) -> 1 | S3: 2200 | T3: 0 | U3: 2200 | V3: 0 | W3: =V3/2 -> 0 | Y3: PSAQALY-cycle | Z3: {=SUMPRODUCT(W3:W363*C3:C363)} -> 20.251463 | AA3: PSAQALY | AB3: =Z3/12 -> 1.6876219
A4: 1 | B4: =(start_age*12+A4)/12 -> 65.083333 | C4: =1/(1+Disc_rate_per_cyc)^$A4 -> 0.99713732 | D4: 0.96078944 | E4: =1-D4/D3 -> 0.039210561 | F4: =-LN(D4/D3)*PSA_SocHRsclr_pfs_VtUs -> 0.04 | G4: =G3*EXP(-F4) -> 0.96078944 | H4: 0.98216103 | I4: =-LN(H4/H3)*PSA_SocHRsclr_os_VtUs -> 0.018 | J4: =J3*EXP(-I4) -> 0.98216103 | K4: =1-(J4/J3) -> 0.017838968 | L4: {=_xlfn.XLOOKUP(B4:B363,DATA_ONS!A7:A107,DATA_ONS!P7:P107,,-1)} -> 0.00083095383 | M4: =MAX(K4:L4) -> 0.017838968 | N4: =N3*(1-M4) -> 0.98216103 | O4: 0.96078944 | P4: =N4-O4 -> 0.021371593 | Q4: =1-N4 -> 0.017838968 | R4: =SUM(O4:Q4) -> 1 | S4: {=soc_pfs_stt*(soc_price+Mntr_Adm_cst_VtUs)} -> 2305.8947 | T4: {=(Subsq_PD_cst_VtUs+Mntr_Adm_cst_VtUs)*soc_pd_stt} -> 22.440173 | U4: =(S3+T3+S4+T4)/2 -> 2264.1674 | V4: {=pfs_ulty_VtUs*soc_pfs_stt+pd_ulty_VtUs*soc_pd_stt} -> 0.76010156 | W4: =(V3+V4)/2 -> 0.38005078 | Y4: PSACOST | Z4: {=SUMPRODUCT(U3:U363*C3:C363)} -> 55570.463
A5: 2 | B5: =(start_age*12+A5)/12 -> 65.166667 | C5: =1/(1+Disc_rate_per_cyc)^$A5 -> 0.99428283 | D5: 0.91220013 | E5: =1-D5/D4 -> 0.050572273 | F5: =-LN(D5/D4)*PSA_SocHRsclr_pfs_VtUs -> 0.051895868 | G5: =G4*EXP(-F5) -> 0.91220013 | H5: 0.96215103 | I5: =-LN(H5/H4)*PSA_SocHRsclr_os_VtUs -> 0.020583845 | J5: =J4*EXP(-I5) -> 0.96215103 | K5: =1-(J5/J4) -> 0.020373443 | L5: 0.00083095383 | M5: =MAX(K5:L5) -> 0.020373443 | N5: =N4*(1-M5) -> 0.96215103 | O5: 0.91220013 | P5: =N5-O5 -> 0.049950897 | Q5: =1-N5 -> 0.03784897 | R5: =SUM(O5:Q5) -> 1 | S5: 2189.2803 | T5: 52.448442 | U5: =(S4+T4+S5+T5)/2 -> 2285.0318 | V5: 0.73649155 | W5: =(V4+V5)/2 -> 0.74829656
A6: 3 | B6: =(start_age*12+A6)/12 -> 65.25 | C6: =1/(1+Disc_rate_per_cyc)^$A6 -> 0.99143652 | D6: 0.86114902 | E6: =1-D6/D5 -> 0.055964818 | F6: =-LN(D6/D5)*PSA_SocHRsclr_pfs_VtUs -> 0.057591844 | G6: =G5*EXP(-F6) -> 0.86114902 | H6: 0.94150968 | I6: =-LN(H6/H5)*PSA_SocHRsclr_os_VtUs -> 0.021686807 | J6: =J5*EXP(-I6) -> 0.94150968 | K6: =1-(J6/J5) -> 0.021453339 | L6: 0.00083095383 | M6: =MAX(K6:L6) -> 0.021453339 | N6: =N5*(1-M6) -> 0.94150968 | O6: 0.86114902 | P6: =N6-O6 -> 0.080360659 | Q6: =1-N6 -> 0.058490322 | R6: =SUM(O6:Q6) -> 1 | S6: 2066.7576 | T6: 84.378692 | U6: =(S5+T5+S6+T6)/2 -> 2196.4325 | V6: 0.71187656 | W6: =(V5+V6)/2 -> 0.72418406
A7: 4 | B7: =(start_age*12+A7)/12 -> 65.333333 | C7: =1/(1+Disc_rate_per_cyc)^$A7 -> 0.98859835 | D7: 0.80967587 | E7: =1-D7/D6 -> 0.059772633 | F7: =-LN(D7/D6)*PSA_SocHRsclr_pfs_VtUs -> 0.061633553 | G7: =G6*EXP(-F7) -> 0.80967587 | H7: 0.92062151 | I7: =-LN(H7/H6)*PSA_SocHRsclr_os_VtUs -> 0.02243563 | J7: =J6*EXP(-I7) -> 0.92062151 | K7: =1-(J7/J6) -> 0.022185823 | L7: 0.00083095383 | M7: =MAX(K7:L7) -> 0.022185823 | N7: =N6*(1-M7) -> 0.92062151 | O7: 0.80967587 | P7: =N7-O7 -> 0.11094564 | Q7: =1-N7 -> 0.079378489 | R7: =SUM(O7:Q7) -> 1 | S7: 1943.2221 | T7: 116.49292 | U7: =(S6+T6+S7+T7)/2 -> 2105.4257 | V7: 0.68702 | W7: =(V6+V7)/2 -> 0.69944828
A8: 5 | B8: =(start_age*12+A8)/12 -> 65.416667 | C8: =1/(1+Disc_rate_per_cyc)^$A8 -> 0.98576831 | D8: 0.75885396 | E8: =1-D8/D7 -> 0.062768223 | F8: =-LN(D8/D7)*PSA_SocHRsclr_pfs_VtUs -> 0.064824667 | G8: =G7*EXP(-F8) -> 0.75885396 | H8: 0.89968039 | I8: =-LN(H8/H7)*PSA_SocHRsclr_os_VtUs -> 0.023009423 | J8: =J7*EXP(-I8) -> 0.89968039 | K8: =1-(J8/J7) -> 0.022746725 | L8: 0.00083095383 | M8: =MAX(K8:L8) -> 0.022746725 | N8: =N7*(1-M8) -> 0.89968039 | O8: 0.75885396 | P8: =N8-O8 -> 0.14082643 | Q8: =1-N8 -> 0.10031961 | R8: =SUM(O8:Q8) -> 1 | S8: 1821.2495 | T8: 147.86775 | U8: =(S7+T7+S8+T8)/2 -> 2014.4161 | V8: 0.6623193 | W8: =(V7+V8)/2 -> 0.67466965
A9: 6 | B9: =(start_age*12+A9)/12 -> 65.5 | C9: =1/(1+Disc_rate_per_cyc)^$A9 -> 0.98294637 | D9: 0.7093313 | E9: =1-D9/D8 -> 0.065259798 | F9: =-LN(D9/D8)*PSA_SocHRsclr_pfs_VtUs -> 0.067486647 | G9: =G8*EXP(-F9) -> 0.7093313 | H9: 0.87880437 | I9: =-LN(H9/H8)*PSA_SocHRsclr_os_VtUs -> 0.023477265 | J9: =J8*EXP(-I9) -> 0.87880437 | K9: =1-(J9/J8) -> 0.023203818 | L9: 0.00083095383 | M9: =MAX(K9:L9) -> 0.023203818 | N9: =N8*(1-M9) -> 0.87880437 | O9: 0.7093313 | P9: =N9-O9 -> 0.16947306 | Q9: =1-N9 -> 0.12119563 | R9: =SUM(O9:Q9) -> 1 | S9: 1702.3951 | T9: 177.94672 | U9: =(S8+T8+S9+T9)/2 -> 1924.7295 | V9: 0.63801495 | W9: =(V8+V9)/2 -> 0.65016713
A10: 7 | B10: =(start_age*12+A10)/12 -> 65.583333 | C10: =1/(1+Disc_rate_per_cyc)^$A10 -> 0.98013251 | D10: 0.66151906 | E10: =1-D10/D9 -> 0.067404673 | F10: =-LN(D10/D9)*PSA_SocHRsclr_pfs_VtUs -> 0.069783906 | G10: =G9*EXP(-F10) -> 0.66151906 | H10: 0.8580726 | I10: =-LN(H10/H9)*PSA_SocHRsclr_os_VtUs -> 0.0238736 | J10: =J9*EXP(-I10) -> 0.8580726 | K10: =1-(J10/J9) -> 0.02359088 | L10: 0.00083095383 | M10: =MAX(K10:L10) -> 0.02359088 | N10: =N9*(1-M10) -> 0.8580726 | O10: 0.66151906 | P10: =N10-O10 -> 0.19655354 | Q10: =1-N10 -> 0.1419274 | R10: =SUM(O10:Q10) -> 1 | S10: 1587.6457 | T10: 206.38122 | U10: =(S9+T9+S10+T10)/2 -> 1837.1844 | V10: 0.61426164 | W10: =(V9+V10)/2 -> 0.62613829
A11: 8 | B11: =(start_age*12+A11)/12 -> 65.666667 | C11: =1/(1+Disc_rate_per_cyc)^$A11 -> 0.97732671 | D11: 0.61567916 | E11: =1-D11/D10 -> 0.069294907 | F11: =-LN(D11/D10)*PSA_SocHRsclr_pfs_VtUs -> 0.071812816 | G11: =G10*EXP(-F11) -> 0.61567916 | H11: 0.83754122 | I11: =-LN(H11/H10)*PSA_SocHRsclr_os_VtUs -> 0.024218226 | J11: =J10*EXP(-I11) -> 0.83754122 | K11: =1-(J11/J10) -> 0.023927318 | L11: 0.00083095383 | M11: =MAX(K11:L11) -> 0.023927318 | N11: =N10*(1-M11) -> 0.83754122 | O11: 0.61567916 | P11: =N11-O11 -> 0.22186207 | Q11: =1-N11 -> 0.16245878 | R11: =SUM(O11:Q11) -> 1 | S11: 1477.63 | T11: 232.95517 | U11: =(S10+T10+S11+T11)/2 -> 1752.3061 | V11: 0.59116078 | W11: =(V10+V11)/2 -> 0.60271121
A12: 9 | B12: =(start_age*12+A12)/12 -> 65.75 | C12: =1/(1+Disc_rate_per_cyc)^$A12 -> 0.97452893 | D12: 0.57197248 | E12: =1-D12/D11 -> 0.070989377 | F12: =-LN(D12/D11)*PSA_SocHRsclr_pfs_VtUs -> 0.073635105 | G12: =G11*EXP(-F12) -> 0.57197248 | H12: 0.81725149 | I12: =-LN(H12/H11)*PSA_SocHRsclr_os_VtUs -> 0.024523617 | J12: =J11*EXP(-I12) -> 0.81725149 | K12: =1-(J12/J11) -> 0.024225356 | L12: 0.00083095383 | M12: =MAX(K12:L12) -> 0.024225356 | N12: =N11*(1-M12) -> 0.81725149 | O12: 0.57197248 | P12: =N12-O12 -> 0.24527901 | Q12: =1-N12 -> 0.18274851 | R12: =SUM(O12:Q12) -> 1 | S12: 1372.7339 | T12: 257.54296 | U12: =(S11+T11+S12+T12)/2 -> 1670.431 | V12: 0.56877804 | W12: =(V11+V12)/2 -> 0.57996941
A13: 10 | B13: =(start_age*12+A13)/12 -> 65.833333 | C13: =1/(1+Disc_rate_per_cyc)^$A13 -> 0.97173917 | D13: 0.53048835 | E13: =1-D13/D12 -> 0.072528182 | F13: =-LN(D13/D12)*PSA_SocHRsclr_pfs_VtUs -> 0.07529287 | G13: =G12*EXP(-F13) -> 0.53048835 | H13: 0.79723437 | I13: =-LN(H13/H12)*PSA_SocHRsclr_os_VtUs -> 0.024798162 | J13: =J12*EXP(-I13) -> 0.79723437 | K13: =1-(J13/J12) -> 0.024493213 | L13: 0.00083095383 | M13: =MAX(K13:L13) -> 0.024493213 | N13: =N12*(1-M13) -> 0.79723437 | O13: 0.53048835 | P13: =N13-O13 -> 0.26674602 | Q13: =1-N13 -> 0.20276563 | R13: =SUM(O13:Q13) -> 1 | S13: 1273.172 | T13: 280.08332 | U13: =(S12+T12+S13+T13)/2 -> 1591.7661 | V13: 0.54715393 | W13: =(V12+V13)/2 -> 0.55796598
A14: 11 | B14: =(start_age*12+A14)/12 -> 65.916667 | C14: =1/(1+Disc_rate_per_cyc)^$A14 -> 0.96895739 | D14: 0.49126407 | E14: =1-D14/D13 -> 0.073939952 | F14: =-LN(D14/D13)*PSA_SocHRsclr_pfs_VtUs -> 0.0768162 | G14: =G13*EXP(-F14) -> 0.49126407 | H14: 0.77751343 | I14: =-LN(H14/H13)*PSA_SocHRsclr_os_VtUs -> 0.025047786 | J14: =J13*EXP(-I14) -> 0.77751343 | K14: =1-(J14/J13) -> 0.024736693 | L14: 0.00083095383 | M14: =MAX(K14:L14) -> 0.024736693 | N14: =N13*(1-M14) -> 0.77751343 | O14: 0.49126407 | P14: =N14-O14 -> 0.28624936 | Q14: =1-N14 -> 0.22248657 | R14: =SUM(O14:Q14) -> 1 | S14: 1179.0338 | T14: 300.56183 | U14: =(S13+T13+S14+T14)/2 -> 1516.4255 | V14: 0.52631066 | W14: =(V13+V14)/2 -> 0.53673229
A15: 12 | B15: =(start_age*12+A15)/12 -> 66 | C15: =1/(1+Disc_rate_per_cyc)^$A15 -> 0.96618357 | D15: 0.45429847 | E15: =1-D15/D14 -> 0.075245887 | F15: =-LN(D15/D14)*PSA_SocHRsclr_pfs_VtUs -> 0.078227401 | G15: =G14*EXP(-F15) -> 0.45429847 | H15: 0.75810666 | I15: =-LN(H15/H14)*PSA_SocHRsclr_os_VtUs -> 0.025276833 | J15: =J14*EXP(-I15) -> 0.75810666 | K15: =1-(J15/J14) -> 0.024960048 | L15: 0.00093428598 | M15: =MAX(K15:L15) -> 0.024960048 | N15: =N14*(1-M15) -> 0.75810666 | O15: 0.45429847 | P15: =N15-O15 -> 0.30380819 | Q15: =1-N15 -> 0.24189334 | R15: =SUM(O15:Q15) -> 1 | S15: 1090.3163 | T15: 318.9986 | U15: =(S14+T14+S15+T15)/2 -> 1444.4553 | V15: 0.5062569 | W15: =(V14+V15)/2 -> 0.51628378
A16: 13 | B16: =(start_age*12+A16)/12 -> 66.083333 | C16: =1/(1+Disc_rate_per_cyc)^$A16 -> 0.9634177 | D16: 0.41956183 | E16: =1-D16/D15 -> 0.076462156 | F16: =-LN(D16/D15)*PSA_SocHRsclr_pfs_VtUs -> 0.079543501 | G16: =G15*EXP(-F16) -> 0.41956183 | H16: 0.73902777 | I16: =-LN(H16/H15)*PSA_SocHRsclr_os_VtUs -> 0.025488587 | J16: =J15*EXP(-I16) -> 0.73902777 | K16: =1-(J16/J15) -> 0.025166496 | L16: 0.00093428598 | M16: =MAX(K16:L16) -> 0.025166496 | N16: =N15*(1-M16) -> 0.73902777 | O16: 0.41956183 | P16: =N16-O16 -> 0.31946594 | Q16: =1-N16 -> 0.26097223 | R16: =SUM(O16:Q16) -> 1 | S16: 1006.9484 | T16: 335.43924 | U16: =(S15+T15+S16+T16)/2 -> 1375.8513 | V16: 0.4869912 | W16: =(V15+V16)/2 -> 0.49662405
... A363: 360 | B363: =(start_age*12+A363)/12 -> 95 | C363: =1/(1+Disc_rate_per_cyc)^$A363 -> 0.35627841 | D363: 5.0599618e-21 | E363: =1-D363/D362 -> 0.14421245 | F363: =-LN(D363/D362)*PSA_SocHRsclr_pfs_VtUs -> 0.15573312 | G363: =G362*EXP(-F363) -> 5.0599618e-21 | H363: 8.5155893e-06 | I363: =-LN(H363/H362)*PSA_SocHRsclr_os_VtUs -> 0.035664412 | J363: =J362*EXP(-I363) -> 8.5155893e-06 | K363: =1-(J363/J362) -> 0.03503593 | L363: 0.023605097 | M363: =MAX(K363:L363) -> 0.03503593 | N363: =N362*(1-M363) -> 8.5155893e-06 | O363: 5.0599618e-21 | P363: =N363-O363 -> 8.5155893e-06 | Q363: =1-N363 -> 0.99999148 | R363: =SUM(O363:Q363) -> 1 | S363: 1.2143908e-17 | T363: 0.0089413687 | U363: =(S362+T362+S363+T363)/2 -> 0.0091036904 | V363: 4.2577946e-06 | W363: =(V362+V363)/2 -> 4.3350907e-06

Sheet trt_engine
A1: Cycle | B1: Patient Age (Years) | C1: Cumulative Discount Factor | D1: Drug A PFS Probability | E1: Trt PSA PFS HR Adj | F1: Drug A PFS Probability PSA Adj | G1: Drug A Progression Risk | H1: Drug A OS Probability | I1: Trt PSA OS HR Adj | J1: Drug A OS Probability PSA Adj | K1: Implied Death Risk | L1: ONS Mortality Risk | M1: Corrected Death Risk | N1: Adjusted OS Probability | O1: Drug A PFS Membership | P1: Drug A Progressed Membership | Q1: Drug A Death Membership | R1: Sum Check | S1: Drug A Acquisition Cost (£) | T1: Drug A Subsequent Cost (£) | U1: Drug A Total Cost (HCC) (£) | V1: Drug A Utility | W1: Drug A QALYs (HCC)
A2: Cycle | B2: Age | C2: disc_rate_clum | D2: trt_PFS_Prob | E2: Trt_PSA_PFS_HR_Adj | F2: trt_PFS_Prob_psa_adj | G2: trt_prog_risk | H2: trt_OS_Prob | I2: Trt_PSA_OS_HR_Adj | J2: trt_OS_Prob_psa_adj | K2: Impl_dth_rsk | L2: ons_dth_risk | M2: crrct_dth_risk | N2: adj_OS_Prob | O2: trt_pfs_stt | P2: trt_pd_stt | Q2: trt_dth | R2: sum_check | S2: trt_pfs_cst | T2: trt_pd_cst | U2: hcctrt_ttl_cst | V2: trt_utl | W2: hcc_qal_per_cyc | Y2: PSAQALY-cycle | Z2: {=SUMPRODUCT(W3:W363*C3:C363)} -> 28.046339 | AA2: PSAQALY | AB2: =Z2/12 -> 2.3371949
A3: 0 | B3: 65 | C3: =1/(1+Disc_rate_per_cyc)^$A3 -> 1 | D3: {=_xlfn.XLOOKUP(A3:A363,'RRMM_Model_Inputs'!A2:A362,'RRMM_Model_Inputs'!D2:D362)} -> 1 | F3: 1 | H3: {=_xlfn.XLOOKUP(A3:A363,'RRMM_Model_Inputs'!A2:A362,'RRMM_Model_Inputs'!E2:E362)} -> 1 | J3: 1 | N3: 1 | O3: {=trt_PFS_Prob_psa_adj} -> 1 | P3: 0 | Q3: 0 | R3: =SUM(O3:Q3) -> 1 | S3: =IF(A3<24,O3*trt_lst_price*(1-trt_pas_disc),0) -> 1050 | T3: 0 | U3: =S3+T3 -> 1050 | V3: 0 | Y3: PSACOST | Z3: {=SUMPRODUCT(U3:U363*C3:C363)} -> 90331.646
A4: 1 | B4: 65.083333 | C4: =1/(1+Disc_rate_per_cyc)^$A4 -> 0.99713732 | D4: 0.97530991 | E4: =-LN(D4/D3)*psa_hrscl_pfs_VtUs -> 0.025 | F4: =D3*EXP(-E4) -> 0.97530991 | G4: =1-D4/D3 -> 0.024690088 | H4: 0.99004983 | I4: =-LN(H4/H3)*PSA_trtHRsclr_os_VtUs -> 0.01 | J4: =H3*EXP(-I4) -> 0.99004983 | K4: =1-J4/J3 -> 0.0099501663 | L4: {=_xlfn.XLOOKUP(B4:B363,DATA_ONS!A7:A107,DATA_ONS!P7:P107,,-1)} -> 0.00083095383 | M4: =MAX(K4:L4) -> 0.0099501663 | N4: =N3*(1-M4) -> 0.99004983 | O4: 0.97530991 | P4: {=trt_engine!adj_OS_Prob-trt_pfs_stt} -> 0.014739922 | Q4: {=1-trt_engine!adj_OS_Prob} -> 0.0099501663 | R4: =SUM(O4:Q4) -> 1 | S4: =IF(A4<24,O4*trt_lst_price*(1-trt_pas_disc),Mntr_Adm_cst_VtUs) -> 1024.0754 | T4: {=(Subsq_PD_cst_VtUs+Mntr_Adm_cst_VtUs)*trt_pd_stt} -> 15.476918 | U4: =(S4+T4+S3+T3)/2 -> 1044.7762 | V4: =IF(A3<=3,pd_ulty_VtUs-Utlty_AE_Disutlt,pd_ulty_VtUs)*O4+pd_ulty_VtUs*P4 -> 0.59255591 | W4: =(V3+V4)/2 -> 0.29627795
A5: 2 | B5: 65.166667 | C5: =1/(1+Disc_rate_per_cyc)^$A5 -> 0.99428283 | D5: 0.94782189 | E5: =-LN(D5/D4)*psa_hrscl_pfs_VtUs -> 0.028588673 | F5: =D4*EXP(-E5) -> 0.94782189 | G5: =1-D5/D4 -> 0.028183884 | H5: 0.97950758 | I5: =-LN(H5/H4)*PSA_trtHRsclr_os_VtUs -> 0.010705298 | J5: =H4*EXP(-I5) -> 0.97950758 | K5: =1-J5/J4 -> 0.010648201 | L5: 0.00083095383 | M5: =MAX(K5:L5) -> 0.010648201 | N5: =N4*(1-M5) -> 0.97950758 | O5: 0.94782189 | P5: 0.031685693 | Q5: 0.020492416 | R5: =SUM(O5:Q5) -> 1 | S5: =IF(A5<24,O5*trt_lst_price*(1-trt_pas_disc),Mntr_Adm_cst_VtUs) -> 995.21299 | T5: 33.269978 | U5: =(S5+T5+S4+T4)/2 -> 1034.0176 | V5: =IF(A4<=3,pd_ulty_VtUs-Utlty_AE_Disutlt,pd_ulty_VtUs)*O5+pd_ulty_VtUs*P5 -> 0.58453598 | W5: =(V4+V5)/2 -> 0.58854594
A6: 3 | B6: 65.25 | C6: =1/(1+Disc_rate_per_cyc)^$A6 -> 0.99143652 | D6: 0.91969863 | E6: =-LN(D6/D5)*psa_hrscl_pfs_VtUs -> 0.030120565 | F6: =D5*EXP(-E6) -> 0.91969863 | G6: =1-D6/D5 -> 0.029671461 | H6: 0.96880297 | I6: =-LN(H6/H5)*PSA_trtHRsclr_os_VtUs -> 0.010988721 | J6: =H5*EXP(-I6) -> 0.96880297 | K6: =1-J6/J5 -> 0.010928565 | L6: 0.00083095383 | M6: =MAX(K6:L6) -> 0.010928565 | N6: =N5*(1-M6) -> 0.96880297 | O6: 0.91969863 | P6: 0.049104341 | Q6: 0.031197028 | R6: =SUM(O6:Q6) -> 1 | S6: =IF(A6<24,O6*trt_lst_price*(1-trt_pas_disc),Mntr_Adm_cst_VtUs) -> 965.68356 | T6: 51.559558 | U6: =(S6+T6+S5+T5)/2 -> 1022.863 | V6: =IF(A5<=3,pd_ulty_VtUs-Utlty_AE_Disutlt,pd_ulty_VtUs)*O6+pd_ulty_VtUs*P6 -> 0.57637135 | W6: =(V5+V6)/2 -> 0.58045367
A7: 4 | B7: 65.333333 | C7: =1/(1+Disc_rate_per_cyc)^$A7 -> 0.98859835 | D7: 0.89148218 | E7: =-LN(D7/D6)*psa_hrscl_pfs_VtUs -> 0.031160597 | F7: =D6*EXP(-E7) -> 0.89148218 | G7: =1-D7/D6 -> 0.03068011 | H7: 0.95803503 | I7: =-LN(H7/H6)*PSA_trtHRsclr_os_VtUs -> 0.011176919 | J7: =H6*EXP(-I7) -> 0.95803503 | K7: =1-J7/J6 -> 0.01111469 | L7: 0.00083095383 | M7: =MAX(K7:L7) -> 0.01111469 | N7: =N6*(1-M7) -> 0.95803503 | O7: 0.89148218 | P7: 0.066552852 | Q7: 0.041964972 | R7: =SUM(O7:Q7) -> 1 | S7: =IF(A7<24,O7*trt_lst_price*(1-trt_pas_disc),Mntr_Adm_cst_VtUs) -> 936.05628 | T7: 69.880494 | U7: =(S7+T7+S6+T6)/2 -> 1011.5899 | V7: =IF(A6<=3,pd_ulty_VtUs-Utlty_AE_Disutlt,pd_ulty_VtUs)*O7+pd_ulty_VtUs*P7 -> 0.56816573 | W7: =(V6+V7)/2 -> 0.57226854
A8: 5 | B8: 65.416667 | C8: =1/(1+Disc_rate_per_cyc)^$A8 -> 0.98576831 | D8: 0.86344302 | E8: =-LN(D8/D7)*psa_hrscl_pfs_VtUs -> 0.031957532 | F8: =D7*EXP(-E8) -> 0.86344302 | G8: =1-D8/D7 -> 0.031452287 | H8: 0.94725219 | I8: =-LN(H8/H7)*PSA_trtHRsclr_os_VtUs -> 0.011318981 | J8: =H7*EXP(-I8) -> 0.94725219 | K8: =1-J8/J7 -> 0.011255162 | L8: 0.00083095383 | M8: =MAX(K8:L8) -> 0.011255162 | N8: =N7*(1-M8) -> 0.94725219 | O8: 0.86344302 | P8: 0.083809165 | Q8: 0.052747812 | R8: =SUM(O8:Q8) -> 1 | S8: =IF(A8<24,O8*trt_lst_price*(1-trt_pas_disc),Mntr_Adm_cst_VtUs) -> 906.61517 | T8: 87.999624 | U8: =(S8+T8+S7+T7)/2 -> 1000.2758 | V8: =IF(A7<=3,pd_ulty_VtUs-Utlty_AE_Disutlt,pd_ulty_VtUs)*O8+pd_ulty_VtUs*P8 -> 0.47362609 | W8: =(V7+V8)/2 -> 0.52089591
A9: 6 | B9: 65.5 | C9: =1/(1+Disc_rate_per_cyc)^$A9 -> 0.98294637 | D9: 0.83574254 | E9: =-LN(D9/D8)*psa_hrscl_pfs_VtUs -> 0.032607312 | F9: =D8*EXP(-E9) -> 0.83574254 | G9: =1-D9/D8 -> 0.032081425 | H9: 0.93648347 | I9: =-LN(H9/H8)*PSA_trtHRsclr_os_VtUs -> 0.011433494 | J9: =H8*EXP(-I9) -> 0.93648347 | K9: =1-J9/J8 -> 0.01136838 | L9: 0.00083095383 | M9: =MAX(K9:L9) -> 0.01136838 | N9: =N8*(1-M9) -> 0.93648347 | O9: 0.83574254 | P9: 0.10074093 | Q9: 0.063516534 | R9: =SUM(O9:Q9) -> 1 | S9: =IF(A9<24,O9*trt_lst_price*(1-trt_pas_disc),Mntr_Adm_cst_VtUs) -> 877.52967 | T9: 105.77797 | U9: =(S9+T9+S8+T8)/2 -> 988.96122 | V9: =IF(A8<=3,pd_ulty_VtUs-Utlty_AE_Disutlt,pd_ulty_VtUs)*O9+pd_ulty_VtUs*P9 -> 0.46824173 | W9: =(V8+V9)/2 -> 0.47093391
A10: 7 | B10: 65.583333 | C10: =1/(1+Disc_rate_per_cyc)^$A10 -> 0.98013251 | D10: 0.80848556 | E10: =-LN(D10/D9)*psa_hrscl_pfs_VtUs -> 0.033157778 | F10: =D9*EXP(-E10) -> 0.80848556 | G10: =1-D10/D9 -> 0.032614085 | H10: 0.92574818 | I10: =-LN(H10/H9)*PSA_trtHRsclr_os_VtUs -> 0.011529609 | J10: =H9*EXP(-I10) -> 0.92574818 | K10: =1-J10/J9 -> 0.011463398 | L10: 0.00083095383 | M10: =MAX(K10:L10) -> 0.011463398 | N10: =N9*(1-M10) -> 0.92574818 | O10: 0.80848556 | P10: 0.11726262 | Q10: 0.074251817 | R10: =SUM(O10:Q10) -> 1 | S10: =IF(A10<24,O10*trt_lst_price*(1-trt_pas_disc),Mntr_Adm_cst_VtUs) -> 848.90984 | T10: 123.12575 | U10: =(S10+T10+S9+T9)/2 -> 977.67162 | V10: =IF(A9<=3,pd_ulty_VtUs-Utlty_AE_Disutlt,pd_ulty_VtUs)*O10+pd_ulty_VtUs*P10 -> 0.46287409 | W10: =(V9+V10)/2 -> 0.46555791
A11: 8 | B11: 65.666667 | C11: =1/(1+Disc_rate_per_cyc)^$A11 -> 0.97732671 | D11: 0.78174328 | E11: =-LN(D11/D10)*psa_hrscl_pfs_VtUs -> 0.033636425 | F11: =D10*EXP(-E11) -> 0.78174328 | G11: =1-D11/D10 -> 0.03307701 | H11: 0.91506008 | I11: =-LN(H11/H10)*PSA_trtHRsclr_os_VtUs -> 0.011612536 | J11: =H10*EXP(-I11) -> 0.91506008 | K11: =1-J11/J10 -> 0.01154537 | L11: 0.00083095383 | M11: =MAX(K11:L11) -> 0.01154537 | N11: =N10*(1-M11) -> 0.91506008 | O11: 0.78174328 | P11: 0.1333168 | Q11: 0.084939923 | R11: =SUM(O11:Q11) -> 1 | S11: =IF(A11<24,O11*trt_lst_price*(1-trt_pas_disc),Mntr_Adm_cst_VtUs) -> 820.83044 | T11: 139.98264 | U11: =(S11+T11+S10+T10)/2 -> 966.42434 | V11: =IF(A10<=3,pd_ulty_VtUs-Utlty_AE_Disutlt,pd_ulty_VtUs)*O11+pd_ulty_VtUs*P11 -> 0.45753004 | W11: =(V10+V11)/2 -> 0.46020207
A12: 9 | B12: 65.75 | C12: =1/(1+Disc_rate_per_cyc)^$A12 -> 0.97452893 | D12: 0.755565 | E12: =-LN(D12/D11)*psa_hrscl_pfs_VtUs -> 0.034060579 | F12: =D11*EXP(-E12) -> 0.755565 | G12: =1-D12/D11 -> 0.033487047 | H12: 0.90442935 | I12: =-LN(H12/H11)*PSA_trtHRsclr_os_VtUs -> 0.011685528 | J12: =H11*EXP(-I12) -> 0.90442935 | K12: =1-J12/J11 -> 0.011617517 | L12: 0.00083095383 | M12: =MAX(K12:L12) -> 0.011617517 | N12: =N11*(1-M12) -> 0.90442935 | O12: 0.755565 | P12: 0.14886435 | Q12: 0.095570649 | R12: =SUM(O12:Q12) -> 1 | S12: =IF(A12<24,O12*trt_lst_price*(1-trt_pas_disc),Mntr_Adm_cst_VtUs) -> 793.34325 | T12: 156.30757 | U12: =(S12+T12+S11+T11)/2 -> 955.23195 | V12: =IF(A11<=3,pd_ulty_VtUs-Utlty_AE_Disutlt,pd_ulty_VtUs)*O12+pd_ulty_VtUs*P12 -> 0.45221468 | W12: =(V11+V12)/2 -> 0.45487236
A13: 10 | B13: 65.833333 | C13: =1/(1+Disc_rate_per_cyc)^$A13 -> 0.97173917 | D13: 0.72998496 | E13: =-LN(D13/D12)*psa_hrscl_pfs_VtUs -> 0.034441892 | F13: =D12*EXP(-E13) -> 0.72998496 | G13: =1-D13/D12 -> 0.033855521 | H13: 0.89386382 | I13: =-LN(H13/H12)*PSA_trtHRsclr_os_VtUs -> 0.01175076 | J13: =H12*EXP(-I13) -> 0.89386382 | K13: =1-J13/J12 -> 0.011681989 | L13: 0.00083095383 | M13: =MAX(K13:L13) -> 0.011681989 | N13: =N12*(1-M13) -> 0.89386382 | O13: 0.72998496 | P13: 0.16387886 | Q13: 0.10613618 | R13: =SUM(O13:Q13) -> 1 | S13: =IF(A13<24,O13*trt_lst_price*(1-trt_pas_disc),Mntr_Adm_cst_VtUs) -> 766.4842 | T13: 172.0728 | U13: =(S13+T13+S12+T12)/2 -> 944.10391 | V13: =IF(A12<=3,pd_ulty_VtUs-Utlty_AE_Disutlt,pd_ulty_VtUs)*O13+pd_ulty_VtUs*P13 -> 0.44693191 | W13: =(V12+V13)/2 -> 0.44957329
A14: 11 | B14: 65.916667 | C14: =1/(1+Disc_rate_per_cyc)^$A14 -> 0.96895739 | D14: 0.70502646 | E14: =-LN(D14/D13)*psa_hrscl_pfs_VtUs -> 0.034788591 | F14: =D13*EXP(-E14) -> 0.70502646 | G14: =1-D14/D13 -> 0.034190425 | H14: 0.88336959 | I14: =-LN(H14/H13)*PSA_trtHRsclr_os_VtUs -> 0.011809757 | J14: =H13*EXP(-I14) -> 0.88336959 | K14: =1-J14/J13 -> 0.011740296 | L14: 0.00083095383 | M14: =MAX(K14:L14) -> 0.011740296 | N14: =N13*(1-M14) -> 0.88336959 | O14: 0.70502646 | P14: 0.17834313 | Q14: 0.11663041 | R14: =SUM(O14:Q14) -> 1 | S14: =IF(A14<24,O14*trt_lst_price*(1-trt_pas_disc),Mntr_Adm_cst_VtUs) -> 740.27778 | T14: 187.26029 | U14: =(S14+T14+S13+T13)/2 -> 933.04754 | V14: =IF(A13<=3,pd_ulty_VtUs-Utlty_AE_Disutlt,pd_ulty_VtUs)*O14+pd_ulty_VtUs*P14 -> 0.4416848 | W14: =(V13+V14)/2 -> 0.44430835
A15: 12 | B15: 66 | C15: =1/(1+Disc_rate_per_cyc)^$A15 -> 0.96618357 | D15: 0.68070473 | E15: =-LN(D15/D14)*psa_hrscl_pfs_VtUs -> 0.035106712 | F15: =D14*EXP(-E15) -> 0.68070473 | G15: =1-D15/D14 -> 0.03449762 | H15: 0.87295154 | I15: =-LN(H15/H14)*PSA_trtHRsclr_os_VtUs -> 0.011863633 | J15: =H14*EXP(-I15) -> 0.87295154 | K15: =1-J15/J14 -> 0.011793537 | L15: 0.00093428598 | M15: =MAX(K15:L15) -> 0.011793537 | N15: =N14*(1-M15) -> 0.87295154 | O15: 0.68070473 | P15: 0.19224681 | Q15: 0.12704846 | R15: =SUM(O15:Q15) -> 1 | S15: =IF(A15<24,O15*trt_lst_price*(1-trt_pas_disc),Mntr_Adm_cst_VtUs) -> 714.73996 | T15: 201.85915 | U15: =(S15+T15+S14+T14)/2 -> 922.06859 | V15: =IF(A14<=3,pd_ulty_VtUs-Utlty_AE_Disutlt,pd_ulty_VtUs)*O15+pd_ulty_VtUs*P15 -> 0.43647577 | W15: =(V14+V15)/2 -> 0.43908028
A16: 13 | B16: 66.083333 | C16: =1/(1+Disc_rate_per_cyc)^$A16 -> 0.9634177 | D16: 0.65702877 | E16: =-LN(D16/D15)*psa_hrscl_pfs_VtUs -> 0.035400816 | F16: =D15*EXP(-E16) -> 0.65702877 | G16: =1-D16/D15 -> 0.034781536 | H16: 0.86261357 | I16: =-LN(H16/H15)*PSA_trtHRsclr_os_VtUs -> 0.011913224 | J16: =H15*EXP(-I16) -> 0.86261357 | K16: =1-J16/J15 -> 0.011842542 | L16: 0.00093428598 | M16: =MAX(K16:L16) -> 0.011842542 | N16: =N15*(1-M16) -> 0.86261357 | O16: 0.65702877 | P16: 0.2055848 | Q16: 0.13738643 | R16: =SUM(O16:Q16) -> 1 | S16: =IF(A16<24,O16*trt_lst_price*(1-trt_pas_disc),Mntr_Adm_cst_VtUs) -> 689.88021 | T16: 215.86404 | U16: =(S16+T16+S15+T15)/2 -> 911.17168 | V16: =IF(A15<=3,pd_ulty_VtUs-Utlty_AE_Disutlt,pd_ulty_VtUs)*O16+pd_ulty_VtUs*P16 -> 0.43130679 | W16: =(V15+V16)/2 -> 0.43389128
... A363: 360 | B363: 95 | C363: =1/(1+Disc_rate_per_cyc)^$A363 -> 0.35627841 | D363: 9.9821936e-19 | E363: =-LN(D363/D362)*psa_hrscl_pfs_VtUs -> 0.15573312 | F363: =D362*EXP(-E363) -> 9.9821936e-19 | G363: =1-D363/D362 -> 0.14421245 | H363: 3.4645547e-05 | I363: =-LN(H363/H362)*PSA_trtHRsclr_os_VtUs -> 0.035664412 | J363: =H362*EXP(-I363) -> 3.4645547e-05 | K363: =1-J363/J362 -> 0.03503593 | L363: 0.023605097 | M363: =MAX(K363:L363) -> 0.03503593 | N363: =N362*(1-M363) -> 3.4645547e-05 | O363: 9.9821936e-19 | P363: 3.4645547e-05 | Q363: 0.99996535 | R363: =SUM(O363:Q363) -> 1 | S363: =IF(A363<24,O363*trt_lst_price*(1-trt_pas_disc),Mntr_Adm_cst_VtUs) -> 200 | T363: 0.036377825 | U363: =(S363+T363+S362+T362)/2 -> 200.03704 | V363: =IF(A362<=3,pd_ulty_VtUs-Utlty_AE_Disutlt,pd_ulty_VtUs)*O363+pd_ulty_VtUs*P363 -> 1.7322774e-05 | W363: =(V362+V363)/2 -> 1.7637251e-05

Sheet DATA_ONS
A1: National Life Tables, Great Britain, period expectation of life, based on data for the years 2022-2024
A2: This worksheet contains two tables, presented horizontally with one blank column in between the tables.
A3: This worksheet uses notation in the column headers, please see the notation worksheet for explanations.
A4: Back to contents
A5: Males | H5: Females
A6: age | B6: mx | C6: qx | D6: lx | E6: dx | F6: ex | H6: age | I6: mx | J6: qx | K6: lx | L6: dx | M6: ex | O6: MnFqx | P6: MonthlyMnFqx
A7: 0 | B7: 0.004605 | C7: 0.004595 | D7: 100000 | E7: 459.5 | F7: 79.13 | H7: 0 | I7: 0.003635 | J7: 0.003629 | K7: 100000 | L7: 362.9 | M7: 83.03 | O7: =(C7+J7)/2 -> 0.004112 | P7: =1-(1-O7)^(1/12) -> 0.00034331418
A8: 1 | B8: 0.000254 | C8: 0.000254 | D8: 99540.5 | E8: 25.3 | F8: 78.5 | H8: 1 | I8: 0.000211 | J8: 0.000211 | K8: 99637.1 | L8: 21 | M8: 82.33 | O8: =(C8+J8)/2 -> 0.0002325 | P8: =1-(1-O8)^(1/12) -> 1.9377065e-05
A9: 2 | B9: 0.000178 | C9: 0.000178 | D9: 99515.3 | E9: 17.7 | F9: 77.52 | H9: 2 | I9: 0.00014 | J9: 0.00014 | K9: 99616.1 | L9: 13.9 | M9: 81.35 | O9: =(C9+J9)/2 -> 0.000159 | P9: =1-(1-O9)^(1/12) -> 1.3250966e-05
A10: 3 | B10: 0.000115 | C10: 0.000115 | D10: 99497.5 | E10: 11.5 | F10: 76.53 | H10: 3 | I10: 0.000101 | J10: 0.000101 | K10: 99602.2 | L10: 10 | M10: 80.36 | O10: =(C10+J10)/2 -> 0.000108 | P10: =1-(1-O10)^(1/12) -> 9.0004455e-06
A11: 4 | B11: 0.000102 | C11: 0.000102 | D11: 99486 | E11: 10.2 | F11: 75.54 | H11: 4 | I11: 8.3e-05 | J11: 8.3e-05 | K11: 99592.1 | L11: 8.2 | M11: 79.37 | O11: =(C11+J11)/2 -> 9.25e-05 | P11: =1-(1-O11)^(1/12) -> 7.7086602e-06
A12: 5 | B12: 9.7e-05 | C12: 9.7e-05 | D12: 99475.9 | E12: 9.7 | F12: 74.55 | H12: 5 | I12: 6.9e-05 | J12: 6.9e-05 | K12: 99583.9 | L12: 6.9 | M12: 78.37 | O12: =(C12+J12)/2 -> 8.3e-05 | P12: =1-(1-O12)^(1/12) -> 6.9169298e-06
A13: 6 | B13: 8e-05 | C13: 8e-05 | D13: 99466.2 | E13: 7.9 | F13: 73.55 | H13: 6 | I13: 7.5e-05 | J13: 7.5e-05 | K13: 99577 | L13: 7.4 | M13: 77.38 | O13: =(C13+J13)/2 -> 7.75e-05 | P13: =1-(1-O13)^(1/12) -> 6.4585628e-06
A14: 7 | B14: 8e-05 | C14: 8e-05 | D14: 99458.2 | E14: 8 | F14: 72.56 | H14: 7 | I14: 6.2e-05 | J14: 6.2e-05 | K14: 99569.6 | L14: 6.2 | M14: 76.39 | O14: =(C14+J14)/2 -> 7.1e-05 | P14: =1-(1-O14)^(1/12) -> 5.9168592e-06
A15: 8 | B15: 8e-05 | C15: 8e-05 | D15: 99450.2 | E15: 7.9 | F15: 71.56 | H15: 8 | I15: 6.2e-05 | J15: 6.2e-05 | K15: 99563.4 | L15: 6.1 | M15: 75.39 | O15: =(C15+J15)/2 -> 7.1e-05 | P15: =1-(1-O15)^(1/12) -> 5.9168592e-06
A16: 9 | B16: 8.9e-05 | C16: 8.9e-05 | D16: 99442.3 | E16: 8.9 | F16: 70.57 | H16: 9 | I16: 6.1e-05 | J16: 6.1e-05 | K16: 99557.3 | L16: 6.1 | M16: 74.4 | O16: =(C16+J16)/2 -> 7.5e-05 | P16: =1-(1-O16)^(1/12) -> 6.2502149e-06
A17: 10 | B17: 7.2e-05 | C17: 7.2e-05 | D17: 99433.5 | E17: 7.1 | F17: 69.58 | H17: 10 | I17: 7.7e-05 | J17: 7.7e-05 | K17: 99551.2 | L17: 7.7 | M17: 73.4 | O17: =(C17+J17)/2 -> 7.45e-05 | P17: =1-(1-O17)^(1/12) -> 6.2085453e-06
A18: 11 | B18: 9.7e-05 | C18: 9.7e-05 | D18: 99426.3 | E18: 9.7 | F18: 68.58 | H18: 11 | I18: 6.3e-05 | J18: 6.3e-05 | K18: 99543.5 | L18: 6.3 | M18: 72.41 | O18: =(C18+J18)/2 -> 8e-05 | P18: =1-(1-O18)^(1/12) -> 6.6669111e-06
... A107: 100 | B107: 0.501487 | C107: 0.400951 | D107: 995.3 | E107: 399.1 | F107: 1.79 | H107: 100 | I107: 0.420999 | J107: 0.34779 | K107: 2651.5 | L107: 922.2 | M107: 2.12 | O107: =(C107+J107)/2 -> 0.3743705 | P107: =1-(1-O107)^(1/12) -> 0.038329188
